crdp.cp37-win32.pyd
crdp-0.0.1.dist-info/LICENSE.txt
crdp-0.0.1.dist-info/METADATA
crdp-0.0.1.dist-info/WHEEL
crdp-0.0.1.dist-info/top_level.txt
crdp-0.0.1.dist-info/RECORD
